Workbook

Sheet Instructions
A1: EW-Cash Strategy Verification Spreadsheet
A3: Purpose: Manually verify the backtesting pipeline by computing EW-cash
A4: returns for 12 months and comparing against pipeline output.
A6: How to use:
A7: 1. Go to the 'Prices' sheet. Fill in monthly close prices for SPY, TLT, GLD, SHY.
A8: Use the close price on the LAST TRADING DAY of each month.
A9: Also fill in the 200-day SMA for SPY, TLT, GLD on that same date.
A10: You can get these from Yahoo Finance or your pipeline's data cache.
A12: 2. Go to the 'Strategy' sheet. All formulas are pre-built.
A13: Check that the filter signals (above/below 200dma) match your expectations.
A14: Check that weights are 0.3333 when above, 0.0 when below.
A15: Check that cash weight = 1 - sum of asset weights.
... A26: BLACK cells = formulas (don't edit)

Sheet Prices
A1: Month | B1: Date (last trading day) | C1: SPY Close | D1: TLT Close | E1: GLD Close | F1: SHY Close | G1: SPY 200dma | H1: TLT 200dma | I1: GLD 200dma
A2: Dec 2023 (prior) | B2: 45289 | C2: 463.84 | D2: 90.59 | E2: 191.17 | F2: 75.71
A3: Jan 2024 | B3: 45322 | C3: 471.23 | D3: 88.55 | E3: 188.45 | F3: 75.95 | G3: 429.13 | H3: 86.89 | I3: 182.35
A4: Feb 2024 | B4: 45351 | C4: 495.82 | D4: 86.56 | E4: 189.31 | F4: 75.66 | G4: 438.21 | H4: 86.15 | I4: 182.47
A5: Mar 2024 | B5: 45379 | C5: 512.04 | D5: 87.23 | E5: 205.72 | F5: 75.92 | G5: 448.01 | H5: 85.72 | I5: 184.23
A6: Apr 2024 | B6: 45412 | C6: 491.39 | D6: 81.6 | E6: 211.87 | F6: 75.58 | G6: 456.05 | H6: 84.82 | I6: 188.28
A7: May 2024 | B7: 45443 | C7: 516.25 | D7: 83.96 | E7: 215.3 | F7: 76.13 | G7: 464.23 | H7: 84.3 | I7: 192.35
A8: Jun 2024 | B8: 45471 | C8: 534.46 | D8: 85.48 | E8: 215.01 | F8: 76.54 | G8: 473.7 | H8: 84.44 | I8: 195.9
A9: Jul 2024 | B9: 45504 | C9: 540.93 | D9: 88.59 | E9: 226.55 | F9: 77.44 | G9: 487.03 | H9: 85.09 | I9: 201.07
A10: Aug 2024 | B10: 45534 | C10: 553.57 | D10: 90.46 | E10: 231.29 | F10: 78.13 | G10: 500.33 | H10: 86.56 | I10: 206.14
A11: Sep 2024 | B11: 45565 | C11: 565.2 | D11: 92.27 | E11: 243.06 | F11: 78.74 | G11: 511.21 | H11: 87.51 | I11: 211.32
A12: Oct 2024 | B12: 45596 | C12: 560.15 | D12: 87.23 | E12: 253.51 | F12: 78.25 | G12: 523.55 | H12: 87.41 | I12: 218.17
A13: Nov 2024 | B13: 45625 | C13: 593.56 | D13: 88.97 | E13: 245.59 | F13: 78.48 | G13: 533.94 | H13: 87.39 | I13: 223.89
A14: Dec 2024 | B14: 45657 | C14: 579.28 | D14: 83.29 | E14: 242.13 | F14: 78.68 | G14: 543.95 | H14: 87.34 | I14: 229.13
A15: Note: Dec 2023 row is needed to compute Jan 2024 returns.
A16: Note: 200dma values only needed for Jan-Dec 2024 (rows 3-14), not Dec 2023.

Sheet Strategy
A1: Month | B1: SPY Return | C1: TLT Return | D1: GLD Return | E1: SHY Return | F1: SPY > 200dma? | G1: TLT > 200dma? | H1: GLD > 200dma? | I1: SPY Weight | J1: TLT Weight | K1: GLD Weight | L1: Cash Weight | M1: Portfolio Return | N1: Equity
A2: Formula logic: | B2: (Close - Prior Close) / Prior Close | F2: Close > 200dma? TRUE/FALSE | I2: 1/3 if above 200dma, else 0 | L2: 1 - sum(asset weights) | M2: sum(weight * return) | N2: prior equity * (1 + return)
A3: Dec 2023 (signal) | F3: TRUE | G3: TRUE | H3: TRUE
A4: =Prices!A3 -> Jan 2024 | B4: =(Prices!C3-Prices!C2)/Prices!C2 -> 0.015932218 | C4: =(Prices!D3-Prices!D2)/Prices!D2 -> -0.022519042 | D4: =(Prices!E3-Prices!E2)/Prices!E2 -> -0.014228174 | E4: =(Prices!F3-Prices!F2)/Prices!F2 -> 0.0031699908 | F4: =Prices!C3>Prices!G3 -> TRUE | G4: =Prices!D3>Prices!H3 -> TRUE | H4: =Prices!E3>Prices!I3 -> TRUE | I4: =IF(F3,1/3,0) -> 0.33333333 | J4: =IF(G3,1/3,0) -> 0.33333333 | K4: =IF(H3,1/3,0) -> 0.33333333 | L4: =1-I4-J4-K4 -> 0 | M4: =I4*B4+J4*C4+K4*D4+L4*E4 -> -0.0069383326 | N4: =200000*(1+M4) -> 198612.33
A5: =Prices!A4 -> Feb 2024 | B5: =(Prices!C4-Prices!C3)/Prices!C3 -> 0.052182586 | C5: =(Prices!D4-Prices!D3)/Prices!D3 -> -0.022473179 | D5: =(Prices!E4-Prices!E3)/Prices!E3 -> 0.0045635447 | E5: =(Prices!F4-Prices!F3)/Prices!F3 -> -0.0038183015 | F5: =Prices!C4>Prices!G4 -> TRUE | G5: =Prices!D4>Prices!H4 -> TRUE | H5: =Prices!E4>Prices!I4 -> TRUE | I5: =IF(F4,1/3,0) -> 0.33333333 | J5: =IF(G4,1/3,0) -> 0.33333333 | K5: =IF(H4,1/3,0) -> 0.33333333 | L5: =1-I5-J5-K5 -> 0 | M5: =I5*B5+J5*C5+K5*D5+L5*E5 -> 0.011424317 | N5: =N4*(1+M5) -> 200881.34
A6: =Prices!A5 -> Mar 2024 | B6: =(Prices!C5-Prices!C4)/Prices!C4 -> 0.032713485 | C6: =(Prices!D5-Prices!D4)/Prices!D4 -> 0.0077402957 | D6: =(Prices!E5-Prices!E4)/Prices!E4 -> 0.086683218 | E6: =(Prices!F5-Prices!F4)/Prices!F4 -> 0.0034364261 | F6: =Prices!C5>Prices!G5 -> TRUE | G6: =Prices!D5>Prices!H5 -> TRUE | H6: =Prices!E5>Prices!I5 -> TRUE | I6: =IF(F5,1/3,0) -> 0.33333333 | J6: =IF(G5,1/3,0) -> 0.33333333 | K6: =IF(H5,1/3,0) -> 0.33333333 | L6: =1-I6-J6-K6 -> 0 | M6: =I6*B6+J6*C6+K6*D6+L6*E6 -> 0.042378999 | N6: =N5*(1+M6) -> 209394.49
A7: =Prices!A6 -> Apr 2024 | B7: =(Prices!C6-Prices!C5)/Prices!C5 -> -0.040328881 | C7: =(Prices!D6-Prices!D5)/Prices!D5 -> -0.064542015 | D7: =(Prices!E6-Prices!E5)/Prices!E5 -> 0.029895003 | E7: =(Prices!F6-Prices!F5)/Prices!F5 -> -0.0044783983 | F7: =Prices!C6>Prices!G6 -> TRUE | G7: =Prices!D6>Prices!H6 -> FALSE | H7: =Prices!E6>Prices!I6 -> TRUE | I7: =IF(F6,1/3,0) -> 0.33333333 | J7: =IF(G6,1/3,0) -> 0.33333333 | K7: =IF(H6,1/3,0) -> 0.33333333 | L7: =1-I7-J7-K7 -> 0 | M7: =I7*B7+J7*C7+K7*D7+L7*E7 -> -0.024991964 | N7: =N6*(1+M7) -> 204161.31
A8: =Prices!A7 -> May 2024 | B8: =(Prices!C7-Prices!C6)/Prices!C6 -> 0.05059118 | C8: =(Prices!D7-Prices!D6)/Prices!D6 -> 0.028921569 | D8: =(Prices!E7-Prices!E6)/Prices!E6 -> 0.016189173 | E8: =(Prices!F7-Prices!F6)/Prices!F6 -> 0.0072770574 | F8: =Prices!C7>Prices!G7 -> TRUE | G8: =Prices!D7>Prices!H7 -> FALSE | H8: =Prices!E7>Prices!I7 -> TRUE | I8: =IF(F7,1/3,0) -> 0.33333333 | J8: =IF(G7,1/3,0) -> 0 | K8: =IF(H7,1/3,0) -> 0.33333333 | L8: =1-I8-J8-K8 -> 0.33333333 | M8: =I8*B8+J8*C8+K8*D8+L8*E8 -> 0.024685803 | N8: =N7*(1+M8) -> 209201.2
A9: =Prices!A8 -> Jun 2024 | B9: =(Prices!C8-Prices!C7)/Prices!C7 -> 0.035273608 | C9: =(Prices!D8-Prices!D7)/Prices!D7 -> 0.018103859 | D9: =(Prices!E8-Prices!E7)/Prices!E7 -> -0.0013469577 | E9: =(Prices!F8-Prices!F7)/Prices!F7 -> 0.0053855248 | F9: =Prices!C8>Prices!G8 -> TRUE | G9: =Prices!D8>Prices!H8 -> TRUE | H9: =Prices!E8>Prices!I8 -> TRUE | I9: =IF(F8,1/3,0) -> 0.33333333 | J9: =IF(G8,1/3,0) -> 0 | K9: =IF(H8,1/3,0) -> 0.33333333 | L9: =1-I9-J9-K9 -> 0.33333333 | M9: =I9*B9+J9*C9+K9*D9+L9*E9 -> 0.013104058 | N9: =N8*(1+M9) -> 211942.59
A10: =Prices!A9 -> Jul 2024 | B10: =(Prices!C9-Prices!C8)/Prices!C8 -> 0.012105677 | C10: =(Prices!D9-Prices!D8)/Prices!D8 -> 0.03638278 | D10: =(Prices!E9-Prices!E8)/Prices!E8 -> 0.053671922 | E10: =(Prices!F9-Prices!F8)/Prices!F8 -> 0.011758558 | F10: =Prices!C9>Prices!G9 -> TRUE | G10: =Prices!D9>Prices!H9 -> TRUE | H10: =Prices!E9>Prices!I9 -> TRUE | I10: =IF(F9,1/3,0) -> 0.33333333 | J10: =IF(G9,1/3,0) -> 0.33333333 | K10: =IF(H9,1/3,0) -> 0.33333333 | L10: =1-I10-J10-K10 -> 0 | M10: =I10*B10+J10*C10+K10*D10+L10*E10 -> 0.03405346 | N10: =N9*(1+M10) -> 219159.96
A11: =Prices!A10 -> Aug 2024 | B11: =(Prices!C10-Prices!C9)/Prices!C9 -> 0.023367164 | C11: =(Prices!D10-Prices!D9)/Prices!D9 -> 0.021108477 | D11: =(Prices!E10-Prices!E9)/Prices!E9 -> 0.020922534 | E11: =(Prices!F10-Prices!F9)/Prices!F9 -> 0.008910124 | F11: =Prices!C10>Prices!G10 -> TRUE | G11: =Prices!D10>Prices!H10 -> TRUE | H11: =Prices!E10>Prices!I10 -> TRUE | I11: =IF(F10,1/3,0) -> 0.33333333 | J11: =IF(G10,1/3,0) -> 0.33333333 | K11: =IF(H10,1/3,0) -> 0.33333333 | L11: =1-I11-J11-K11 -> 0 | M11: =I11*B11+J11*C11+K11*D11+L11*E11 -> 0.021799392 | N11: =N10*(1+M11) -> 223937.52
A12: =Prices!A11 -> Sep 2024 | B12: =(Prices!C11-Prices!C10)/Prices!C10 -> 0.021009086 | C12: =(Prices!D11-Prices!D10)/Prices!D10 -> 0.020008844 | D12: =(Prices!E11-Prices!E10)/Prices!E10 -> 0.050888495 | E12: =(Prices!F11-Prices!F10)/Prices!F10 -> 0.0078075003 | F12: =Prices!C11>Prices!G11 -> TRUE | G12: =Prices!D11>Prices!H11 -> TRUE | H12: =Prices!E11>Prices!I11 -> TRUE | I12: =IF(F11,1/3,0) -> 0.33333333 | J12: =IF(G11,1/3,0) -> 0.33333333 | K12: =IF(H11,1/3,0) -> 0.33333333 | L12: =1-I12-J12-K12 -> 0 | M12: =I12*B12+J12*C12+K12*D12+L12*E12 -> 0.030635475 | N12: =N11*(1+M12) -> 230797.95
A13: =Prices!A12 -> Oct 2024 | B13: =(Prices!C12-Prices!C11)/Prices!C11 -> -0.0089348903 | C13: =(Prices!D12-Prices!D11)/Prices!D11 -> -0.054622304 | D13: =(Prices!E12-Prices!E11)/Prices!E11 -> 0.0429935 | E13: =(Prices!F12-Prices!F11)/Prices!F11 -> -0.0062230124 | F13: =Prices!C12>Prices!G12 -> TRUE | G13: =Prices!D12>Prices!H12 -> FALSE | H13: =Prices!E12>Prices!I12 -> TRUE | I13: =IF(F12,1/3,0) -> 0.33333333 | J13: =IF(G12,1/3,0) -> 0.33333333 | K13: =IF(H12,1/3,0) -> 0.33333333 | L13: =1-I13-J13-K13 -> 0 | M13: =I13*B13+J13*C13+K13*D13+L13*E13 -> -0.006854565 | N13: =N12*(1+M13) -> 229215.93
A14: =Prices!A13 -> Nov 2024 | B14: =(Prices!C13-Prices!C12)/Prices!C12 -> 0.059644738 | C14: =(Prices!D13-Prices!D12)/Prices!D12 -> 0.019947266 | D14: =(Prices!E13-Prices!E12)/Prices!E12 -> -0.031241371 | E14: =(Prices!F13-Prices!F12)/Prices!F12 -> 0.0029392971 | F14: =Prices!C13>Prices!G13 -> TRUE | G14: =Prices!D13>Prices!H13 -> TRUE | H14: =Prices!E13>Prices!I13 -> TRUE | I14: =IF(F13,1/3,0) -> 0.33333333 | J14: =IF(G13,1/3,0) -> 0 | K14: =IF(H13,1/3,0) -> 0.33333333 | L14: =1-I14-J14-K14 -> 0.33333333 | M14: =I14*B14+J14*C14+K14*D14+L14*E14 -> 0.010447555 | N14: =N13*(1+M14) -> 231610.68
A15: =Prices!A14 -> Dec 2024 | B15: =(Prices!C14-Prices!C13)/Prices!C13 -> -0.024058225 | C15: =(Prices!D14-Prices!D13)/Prices!D13 -> -0.063841744 | D15: =(Prices!E14-Prices!E13)/Prices!E13 -> -0.014088522 | E15: =(Prices!F14-Prices!F13)/Prices!F13 -> 0.00254842 | F15: =Prices!C14>Prices!G14 -> TRUE | G15: =Prices!D14>Prices!H14 -> FALSE | H15: =Prices!E14>Prices!I14 -> TRUE | I15: =IF(F14,1/3,0) -> 0.33333333 | J15: =IF(G14,1/3,0) -> 0.33333333 | K15: =IF(H14,1/3,0) -> 0.33333333 | L15: =1-I15-J15-K15 -> 0 | M15: =I15*B15+J15*C15+K15*D15+L15*E15 -> -0.033996164 | N15: =N14*(1+M15) -> 223736.8

Sheet Comparison
A1: Month | B1: Spreadsheet Equity | C1: Pipeline Equity | D1: Difference ($) | E1: Difference (%)
A2: =Strategy!A4 -> Jan 2024 | B2: =Strategy!N4 -> 198612.33 | C2: 199030.53 | D2: =IF(C2="","",B2-C2) -> -418.19651 | E2: =IF(C2="","",D2/C2) -> -0.0021011677
A3: =Strategy!A5 -> Feb 2024 | B3: =Strategy!N5 -> 200881.34 | C3: 201243.14 | D3: =IF(C3="","",B3-C3) -> -361.79621 | E3: =IF(C3="","",D3/C3) -> -0.0017978064
A4: =Strategy!A6 -> Mar 2024 | B4: =Strategy!N6 -> 209394.49 | C4: 209724.27 | D4: =IF(C4="","",B4-C4) -> -329.77584 | E4: =IF(C4="","",D4/C4) -> -0.0015724257
A5: =Strategy!A7 -> Apr 2024 | B5: =Strategy!N7 -> 204161.31 | C5: 204425.36 | D5: =IF(C5="","",B5-C5) -> -264.04557 | E5: =IF(C5="","",D5/C5) -> -0.0012916478
A6: =Strategy!A8 -> May 2024 | B6: =Strategy!N8 -> 209201.2 | C6: 209483.58 | D6: =IF(C6="","",B6-C6) -> -282.37951 | E6: =IF(C6="","",D6/C6) -> -0.0013479792
A7: =Strategy!A9 -> Jun 2024 | B7: =Strategy!N9 -> 211942.59 | C7: 212240.21 | D7: =IF(C7="","",B7-C7) -> -297.62479 | E7: =IF(C7="","",D7/C7) -> -0.0014023016
A8: =Strategy!A10 -> Jul 2024 | B8: =Strategy!N10 -> 219159.96 | C8: 220746.35 | D8: =IF(C8="","",B8-C8) -> -1586.3865 | E8: =IF(C8="","",D8/C8) -> -0.0071864678
A9: =Strategy!A11 -> Aug 2024 | B9: =Strategy!N11 -> 223937.52 | C9: 225753.15 | D9: =IF(C9="","",B9-C9) -> -1815.6327 | E9: =IF(C9="","",D9/C9) -> -0.0080425574
A10: =Strategy!A12 -> Sep 2024 | B10: =Strategy!N12 -> 230797.95 | C10: 232735.35 | D10: =IF(C10="","",B10-C10) -> -1937.4004 | E10: =IF(C10="","",D10/C10) -> -0.0083244786
A11: =Strategy!A13 -> Oct 2024 | B11: =Strategy!N13 -> 229215.93 | C11: 231024.19 | D11: =IF(C11="","",B11-C11) -> -1808.26 | E11: =IF(C11="","",D11/C11) -> -0.0078271456
A12: =Strategy!A14 -> Nov 2024 | B12: =Strategy!N14 -> 231610.68 | C12: 233394.83 | D12: =IF(C12="","",B12-C12) -> -1784.154 | E12: =IF(C12="","",D12/C12) -> -0.0076443596
A13: =Strategy!A15 -> Dec 2024 | B13: =Strategy!N15 -> 223736.8 | C13: 225268.15 | D13: =IF(C13="","",B13-C13) -> -1531.3485 | E13: =IF(C13="","",D13/C13) -> -0.0067978916
A15: Max Abs Difference (%) | E15: {=IF(COUNT(E2:E13)=0,"",MAX(ABS(E2:E13)))} -> 0.0083244786
A16: Verdict | E16: =IF(E15="","",IF(E15<0.01,"PASS","FAIL")) -> PASS
A18: Note: Differences (<1%) are expected from daily vs monthly compounding, slippage (2 bps in pipeline, none in spreadsheet), and intra-month weight drift. Differences >2% indicate a bug.
A21: Pipeline equity must be rebased to $200K: multiply each value by 200000 / (Dec 2023 equity) before pasting
